arp_jarvis_selection_service-0.3.8.dist-info/licenses/LICENSE
jarvis_selection_service/__init__.py
jarvis_selection_service/__main__.py
jarvis_selection_service/app.py
jarvis_selection_service/llm_assets.py
jarvis_selection_service/node_registry_client.py
jarvis_selection_service/service.py
jarvis_selection_service/strategy.py
jarvis_selection_service/utils.py
scripts/send_request.py
arp_jarvis_selection_service-0.3.8.dist-info/METADATA
arp_jarvis_selection_service-0.3.8.dist-info/WHEEL
arp_jarvis_selection_service-0.3.8.dist-info/entry_points.txt
arp_jarvis_selection_service-0.3.8.dist-info/top_level.txt
arp_jarvis_selection_service-0.3.8.dist-info/RECORD
