Metadata-Version: 2.4
Name: arp-jarvis-selection-service
Version: 0.3.8
Summary: JARVIS Selection Service implementation for the ARP Standard (spec/v1).
Author: Agent Runtime Protocol
License-Expression: MIT
Requires-Python: >=3.10
License-File: LICENSE
Requires-Dist: arp-standard-client==0.3.7
Requires-Dist: arp-standard-server==0.3.7
Requires-Dist: arp-standard-model==0.3.7
Requires-Dist: arp-llm==0.1.1
Requires-Dist: uvicorn>=0.29.0
Provides-Extra: dev
Requires-Dist: pyright>=1.1.0; extra == "dev"
Requires-Dist: pytest>=7; extra == "dev"
Requires-Dist: pytest-cov>=4; extra == "dev"
Dynamic: license-file
